python_zimuzu-0.0.1.dist-info/DESCRIPTION.rst
python_zimuzu-0.0.1.dist-info/METADATA
python_zimuzu-0.0.1.dist-info/RECORD
python_zimuzu-0.0.1.dist-info/WHEEL
python_zimuzu-0.0.1.dist-info/entry_points.txt
python_zimuzu-0.0.1.dist-info/metadata.json
python_zimuzu-0.0.1.dist-info/top_level.txt
tests/__init__.py
zimuzu/__init__.py
zimuzu/__main__.py
zimuzu/command.py
zimuzu/config.py
zimuzu/core.py
zimuzu/env.py
zimuzu/exception.py
zimuzu/filter.py
zimuzu/handler.py
zimuzu/log.py
