Metadata-Version: 2.0
Name: python-zimuzu
Version: 0.0.1
Summary: 
Requires-Dist: click (>=6.6)
Requires-Dist: schedule (>=0.4.2)
